nds/asset/asset_pb2.py
nds/audit/rationale_pb2.py
nds/common/common_pb2.py
nds/common/v1/common_v1_pb2.py
nds/context/context_pb2.py
nds/event/event_pb2.py
nds/event/v1/event_v1_pb2.py
nds/identity/identity_pb2.py
nds/identity/v1/identity_v1_pb2.py
nds/ledger/v1/ledger_pb2.py
nds/memory/v1/memory_pb2.py
nds/metadata/v1/metadata_pb2.py
nds/policy/policy_pb2.py
nds/projection/projection_pb2.py
nds/query/query_pb2.py
nds/sync/v1/sync_pb2.py
nds/transaction/transaction_pb2.py
noie_nds_api-3.0.6.dist-info/METADATA
noie_nds_api-3.0.6.dist-info/WHEEL
noie_nds_api-3.0.6.dist-info/top_level.txt
noie_nds_api-3.0.6.dist-info/RECORD
