Metadata-Version: 2.4
Name: noie-nds-api
Version: 3.0.6
Summary: NDS Protocol Buffers types for Python (generated from nds-api/spec).
Author: Misty4119
License-Expression: Apache-2.0
Project-URL: Homepage, https://github.com/Misty4119/nds-api
Project-URL: Repository, https://github.com/Misty4119/nds-api
Project-URL: Issues, https://github.com/Misty4119/nds-api/issues
Requires-Python: >=3.14
Requires-Dist: protobuf<7,>=6.31.1
